MANIFEST.in
README.md
README.rst
setup.py
okcupyd/__init__.py
okcupyd/attractiveness_finder.py
okcupyd/details.py
okcupyd/errors.py
okcupyd/essay.py
okcupyd/filter.py
okcupyd/helpers.py
okcupyd/looking_for.py
okcupyd/magicnumbers.py
okcupyd/messaging.py
okcupyd/photo.py
okcupyd/profile.py
okcupyd/profile_copy.py
okcupyd/question.py
okcupyd/search.py
okcupyd/session.py
okcupyd/settings.py
okcupyd/statistics.py
okcupyd/user.py
okcupyd/xpath.py
okcupyd.egg-info/PKG-INFO
okcupyd.egg-info/SOURCES.txt
okcupyd.egg-info/dependency_links.txt
okcupyd.egg-info/entry_points.txt
okcupyd.egg-info/requires.txt
okcupyd.egg-info/top_level.txt
okcupyd/db/__init__.py
okcupyd/db/adapters.py
okcupyd/db/mailbox.py
okcupyd/db/types.py
okcupyd/db/user.py
okcupyd/db/model/__init__.py
okcupyd/db/model/message.py
okcupyd/db/model/message_thread.py
okcupyd/db/model/user.py
okcupyd/tasks/__init__.py
okcupyd/tasks/copy.py
okcupyd/tasks/db.py
okcupyd/tasks/site.py
okcupyd/util/__init__.py
okcupyd/util/compose.py
okcupyd/util/currying.py
okcupyd/util/fetchable.py
okcupyd/util/misc.py
okcupyd_testing/__init__.py
okcupyd_testing/conftest.py
okcupyd_testing/util.py