Metadata-Version: 1.1
Name: okcupyd
Version: 0.9.0
Summary: A package for interacting with okcupid.com
Home-page: https://github.com/IvanMalison/okcupyd
Author: Ivan Malison
Author-email: ivanmalison@gmail.com
License: MIT
Keywords: okcupid,okcupyd,pyokc,online dating
Platform: UNKNOWN
Classifier: Development Status :: 3 - Alpha
Classifier: License :: OSI Approved :: MIT License
Classifier: Programming Language :: Python :: 3
Classifier: Topic :: Utilities
